{
  "slice": "900",
  "verdict": "approved",
  "timestamp": "2026-04-11T00:00:00Z",
  "ac_validation": [
    {
      "ac_id": "AC-001",
      "status": "pass",
      "evidence": "Arquivo src/Utils/Greeting.php existe com metodo greet(string $name): string retornando 'Hello, {name}!'. Testes 'greet returns Hello name' e 'greet returns Hello with any name' passam com exit 0."
    },
    {
      "ac_id": "AC-002",
      "status": "pass",
      "evidence": "greet('') retorna 'Hello, World!' conforme logica condicional na linha 9 da implementacao. Teste 'greet with empty string returns Hello World' passa com exit 0."
    },
    {
      "ac_id": "AC-003",
      "status": "pass",
      "evidence": "Arquivo tests/Unit/GreetingTest.php existe com 3 testes Pest cobrindo AC-001 (2 testes) e AC-002 (1 teste). Todos passam: 3 passed (3 assertions), Duration 0.17s, exit 0."
    }
  ],
  "product_concerns": [],
  "findings": [],
  "summary": "Slice 900 smoke-test aprovado: todos os 3 ACs atendidos, 3 testes Pest passam com exit 0.",
  "next_action": "proceed"
}
